coinespy/__init__.py
coinespy/coines.py
coinespy/libcoines_32.dll
coinespy/libcoines_32.so
coinespy/libcoines_64.dll
coinespy/libcoines_64.so
coinespy_lib-1.1.1.dist-info/LICENSE.txt
coinespy_lib-1.1.1.dist-info/METADATA
coinespy_lib-1.1.1.dist-info/WHEEL
coinespy_lib-1.1.1.dist-info/top_level.txt
coinespy_lib-1.1.1.dist-info/RECORD
