Metadata-Version: 2.1
Name: coinespy-lib
Version: 1.1.1
Summary: Python wrapper for coinesAPI
Home-page: https://www.bosch-sensortec.com/
Author: Bosch Sensortec GmbH
Author-email: vuongthiencuong@gmail.com
Classifier: Programming Language :: Python :: 3
Classifier: Programming Language :: Python :: 2
Classifier: License :: OSI Approved :: BSD License
Classifier: Operating System :: Microsoft :: Windows
Classifier: Operating System :: POSIX :: Linux
Classifier: Operating System :: MacOS :: MacOS X
Requires-Python: >=2.6, <4
License-File: LICENSE.txt
Requires-Dist: flake8
Requires-Dist: lizard
Requires-Dist: pytest
Requires-Dist: pytest-cov
Requires-Dist: pytest-html
